<annotation>
	<folder></folder>
	<filename>fire-69_png.rf.d942e974bdd4cab67f0d159329799a23.jpg</filename>
	<path>fire-69_png.rf.d942e974bdd4cab67f0d159329799a23.jpg</path>
	<source>
		<database>roboflow.com</database>
	</source>
	<size>
		<width>640</width>
		<height>640</height>
		<depth>3</depth>
	</size>
	<segmented>0</segmented>
	<object>
		<name>api</name>
		<pose>Unspecified</pose>
		<truncated>0</truncated>
		<difficult>0</difficult>
		<occluded>0</occluded>
		<bndbox>
			<xmin>525</xmin>
			<xmax>564</xmax>
			<ymin>376</ymin>
			<ymax>485</ymax>
		</bndbox>
	</object>
	<object>
		<name>api</name>
		<pose>Unspecified</pose>
		<truncated>0</truncated>
		<difficult>0</difficult>
		<occluded>0</occluded>
		<bndbox>
			<xmin>314</xmin>
			<xmax>358</xmax>
			<ymin>434</ymin>
			<ymax>477</ymax>
		</bndbox>
	</object>
	<object>
		<name>api</name>
		<pose>Unspecified</pose>
		<truncated>0</truncated>
		<difficult>0</difficult>
		<occluded>0</occluded>
		<bndbox>
			<xmin>81</xmin>
			<xmax>104</xmax>
			<ymin>372</ymin>
			<ymax>411</ymax>
		</bndbox>
	</object>
	<object>
		<name>asap</name>
		<pose>Unspecified</pose>
		<truncated>0</truncated>
		<difficult>0</difficult>
		<occluded>0</occluded>
		<bndbox>
			<xmin>92</xmin>
			<xmax>464</xmax>
			<ymin>7</ymin>
			<ymax>210</ymax>
		</bndbox>
	</object>
	<object>
		<name>asap</name>
		<pose>Unspecified</pose>
		<truncated>0</truncated>
		<difficult>0</difficult>
		<occluded>0</occluded>
		<bndbox>
			<xmin>175</xmin>
			<xmax>216</xmax>
			<ymin>294</ymin>
			<ymax>362</ymax>
		</bndbox>
	</object>
	<object>
		<name>asap</name>
		<pose>Unspecified</pose>
		<truncated>0</truncated>
		<difficult>0</difficult>
		<occluded>0</occluded>
		<bndbox>
			<xmin>282</xmin>
			<xmax>340</xmax>
			<ymin>336</ymin>
			<ymax>412</ymax>
		</bndbox>
	</object>
	<object>
		<name>asap</name>
		<pose>Unspecified</pose>
		<truncated>0</truncated>
		<difficult>0</difficult>
		<occluded>0</occluded>
		<bndbox>
			<xmin>509</xmin>
			<xmax>582</xmax>
			<ymin>46</ymin>
			<ymax>231</ymax>
		</bndbox>
	</object>
	<object>
		<name>asap</name>
		<pose>Unspecified</pose>
		<truncated>0</truncated>
		<difficult>0</difficult>
		<occluded>0</occluded>
		<bndbox>
			<xmin>78</xmin>
			<xmax>125</xmax>
			<ymin>301</ymin>
			<ymax>371</ymax>
		</bndbox>
	</object>
</annotation>
